<?xml version="1.0" encoding="utf-8"?>
<!DOCTYPE hibernate-mapping PUBLIC "-//Hibernate/Hibernate Mapping DTD 3.0//EN"
"http://hibernate.sourceforge.net/hibernate-mapping-3.0.dtd">
<!-- 
    Mapping file autogenerated by MyEclipse Persistence Tools
-->
<hibernate-mapping>
    <class name="com.abe.entity.Users" table="users" catalog="abe">
        <id name="UId" type="java.lang.String">
            <column name="u_id" />
            <generator class="assigned" />
        </id>
        <property name="UNum" type="java.lang.String">
            <column name="u_num" not-null="true" unique="true" />
        </property>
        <property name="UName" type="java.lang.String">
            <column name="u_name" />
        </property>
        <property name="UPass" type="java.lang.String">
            <column name="u_pass" />
        </property>
        <property name="UType" type="java.lang.String">
            <column name="u_type" />
        </property>
        <property name="UCreateTime" type="java.sql.Timestamp">
            <column name="u_create_time" length="19" />
        </property>
        <property name="UPhotoPath" type="java.lang.String">
            <column name="u_photo_path" />
        </property>
        <property name="UNote" type="java.lang.String">
            <column name="u_note" />
        </property>
        <property name="trpId" type="java.lang.String">
            <column name="trp_id" />
        </property>
        <property name="RId" type="java.lang.String">
            <column name="r_id" />
        </property>
    </class>
</hibernate-mapping>
